{
  "hierarchy": {
    "@index": "0",
    "@class": "hierarchy",
    "@rotation": "0",
    "@width": "1080",
    "@height": "2236",
    "android.widget.FrameLayout": {
      "@index": "0",
      "@package": "com.opera.mini.native",
      "@class": "android.widget.FrameLayout",
      "@text": "",
      "@checkable": "false",
      "@checked": "false",
      "@clickable": "false",
      "@enabled": "true",
      "@focusable": "false",
      "@focused": "false",
      "@long-clickable": "false",
      "@password": "false",
      "@scrollable": "false",
      "@selected": "false",
      "@bounds": "[0,0][1080,2236]",
      "@displayed": "true",
      "android.widget.LinearLayout": {
        "@index": "0",
        "@package": "com.opera.mini.native",
        "@class": "android.widget.LinearLayout",
        "@text": "",
        "@checkable": "false",
        "@checked": "false",
        "@clickable": "false",
        "@enabled": "true",
        "@focusable": "false",
        "@focused": "false",
        "@long-clickable": "false",
        "@password": "false",
        "@scrollable": "false",
        "@selected": "false",
        "@bounds": "[0,0][1080,2236]",
        "@displayed": "true",
        "android.widget.FrameLayout": {
          "@index": "0",
          "@package": "com.opera.mini.native",
          "@class": "android.widget.FrameLayout",
          "@text": "",
          "@resource-id": "android:id/content",
          "@checkable": "false",
          "@checked": "false",
          "@clickable": "false",
          "@enabled": "true",
          "@focusable": "false",
          "@focused": "false",
          "@long-clickable": "false",
          "@password": "false",
          "@scrollable": "false",
          "@selected": "false",
          "@bounds": "[0,66][1080,2236]",
          "@displayed": "true",
          "android.widget.FrameLayout": {
            "@index": "0",
            "@package": "com.opera.mini.native",
            "@class": "android.widget.FrameLayout",
            "@text": "",
            "@resource-id": "com.opera.mini.native:id/fragment_container",
            "@checkable": "false",
            "@checked": "false",
            "@clickable": "false",
            "@enabled": "true",
            "@focusable": "false",
            "@focused": "false",
            "@long-clickable": "false",
            "@password": "false",
            "@scrollable": "false",
            "@selected": "false",
            "@bounds": "[0,66][1080,2236]",
            "@displayed": "true",
            "android.widget.LinearLayout": {
              "@index": "0",
              "@package": "com.opera.mini.native",
              "@class": "android.widget.LinearLayout",
              "@text": "",
              "@checkable": "false",
              "@checked": "false",
              "@clickable": "false",
              "@enabled": "true",
              "@focusable": "false",
              "@focused": "false",
              "@long-clickable": "false",
              "@password": "false",
              "@scrollable": "false",
              "@selected": "false",
              "@bounds": "[0,66][1080,2236]",
              "@displayed": "true",
              "android.widget.ScrollView": {
                "@index": "0",
                "@package": "com.opera.mini.native",
                "@class": "android.widget.ScrollView",
                "@text": "",
                "@resource-id": "com.opera.mini.native:id/content",
                "@checkable": "false",
                "@checked": "false",
                "@clickable": "false",
                "@enabled": "true",
                "@focusable": "true",
                "@focused": "false",
                "@long-clickable": "false",
                "@password": "false",
                "@scrollable": "false",
                "@selected": "false",
                "@bounds": "[0,66][1080,1906]",
                "@displayed": "true",
                "android.widget.LinearLayout": {
                  "@index": "0",
                  "@package": "com.opera.mini.native",
                  "@class": "android.widget.LinearLayout",
                  "@text": "",
                  "@checkable": "false",
                  "@checked": "false",
                  "@clickable": "false",
                  "@enabled": "true",
                  "@focusable": "false",
                  "@focused": "false",
                  "@long-clickable": "false",
                  "@password": "false",
                  "@scrollable": "false",
                  "@selected": "false",
                  "@bounds": "[0,66][1080,1023]",
                  "@displayed": "true",
                  "android.widget.ImageView": {
                    "@index": "0",
                    "@package": "com.opera.mini.native",
                    "@class": "android.widget.ImageView",
                    "@text": "",
                    "@resource-id": "com.opera.mini.native:id/logo",
                    "@checkable": "false",
                    "@checked": "false",
                    "@clickable": "false",
                    "@enabled": "true",
                    "@focusable": "false",
                    "@focused": "false",
                    "@long-clickable": "false",
                    "@password": "false",
                    "@scrollable": "false",
                    "@selected": "false",
                    "@bounds": "[463,143][617,297]",
                    "@displayed": "true"
                  },
                  "android.widget.TextView": [
                    {
                      "@index": "1",
                      "@package": "com.opera.mini.native",
                      "@class": "android.widget.TextView",
                      "@text": "Welcome to Opera Mini",
                      "@resource-id": "com.opera.mini.native:id/header_text",
                      "@checkable": "false",
                      "@checked": "false",
                      "@clickable": "false",
                      "@enabled": "true",
                      "@focusable": "false",
                      "@focused": "false",
                      "@long-clickable": "false",
                      "@password": "false",
                      "@scrollable": "false",
                      "@selected": "false",
                      "@bounds": "[66,341][1014,517]",
                      "@displayed": "true"
                    },
                    {
                      "@index": "2",
                      "@package": "com.opera.mini.native",
                      "@class": "android.widget.TextView",
                      "@text": "Data-saving browser",
                      "@resource-id": "com.opera.mini.native:id/explanation_text",
                      "@checkable": "false",
                      "@checked": "false",
                      "@clickable": "false",
                      "@enabled": "true",
                      "@focusable": "false",
                      "@focused": "false",
                      "@long-clickable": "false",
                      "@password": "false",
                      "@scrollable": "false",
                      "@selected": "false",
                      "@bounds": "[66,528][1014,581]",
                      "@displayed": "true"
                    }
                  ],
                  "android.widget.FrameLayout": [
                    {
                      "@index": "3",
                      "@package": "com.opera.mini.native",
                      "@class": "android.widget.FrameLayout",
                      "@text": "",
                      "@checkable": "false",
                      "@checked": "false",
                      "@clickable": "false",
                      "@enabled": "true",
                      "@focusable": "false",
                      "@focused": "false",
                      "@long-clickable": "false",
                      "@password": "false",
                      "@scrollable": "false",
                      "@selected": "false",
                      "@bounds": "[66,647][1014,813]",
                      "@displayed": "true",
                      "android.widget.LinearLayout": {
                        "@index": "0",
                        "@package": "com.opera.mini.native",
                        "@class": "android.widget.LinearLayout",
                        "@text": "",
                        "@resource-id": "com.opera.mini.native:id/block_ads_switch",
                        "@checkable": "false",
                        "@checked": "false",
                        "@clickable": "true",
                        "@enabled": "true",
                        "@focusable": "true",
                        "@focused": "false",
                        "@long-clickable": "false",
                        "@password": "false",
                        "@scrollable": "false",
                        "@selected": "false",
                        "@bounds": "[66,647][1014,813]",
                        "@displayed": "true",
                        "android.widget.LinearLayout": {
                          "@index": "0",
                          "@package": "com.opera.mini.native",
                          "@class": "android.widget.LinearLayout",
                          "@text": "",
                          "@checkable": "false",
                          "@checked": "false",
                          "@clickable": "false",
                          "@enabled": "true",
                          "@focusable": "false",
                          "@focused": "false",
                          "@long-clickable": "false",
                          "@password": "false",
                          "@scrollable": "false",
                          "@selected": "false",
                          "@bounds": "[220,700][838,759]",
                          "@displayed": "true",
                          "android.widget.TextView": {
                            "@index": "0",
                            "@package": "com.opera.mini.native",
                            "@class": "android.widget.TextView",
                            "@text": "Tired of ads? Block them!",
                            "@resource-id": "com.opera.mini.native:id/caption",
                            "@checkable": "false",
                            "@checked": "false",
                            "@clickable": "false",
                            "@enabled": "true",
                            "@focusable": "false",
                            "@focused": "false",
                            "@long-clickable": "false",
                            "@password": "false",
                            "@scrollable": "false",
                            "@selected": "false",
                            "@bounds": "[220,700][816,759]",
                            "@displayed": "true"
                          }
                        },
                        "android.widget.Switch": {
                          "@index": "1",
                          "@package": "com.opera.mini.native",
                          "@class": "android.widget.Switch",
                          "@text": "ON",
                          "@resource-id": "com.opera.mini.native:id/switcher",
                          "@checkable": "true",
                          "@checked": "true",
                          "@clickable": "true",
                          "@enabled": "true",
                          "@focusable": "true",
                          "@focused": "false",
                          "@long-clickable": "false",
                          "@password": "false",
                          "@scrollable": "false",
                          "@selected": "false",
                          "@bounds": "[838,664][970,796]",
                          "@displayed": "true"
                        }
                      },
                      "android.widget.ImageView": {
                        "@index": "1",
                        "@package": "com.opera.mini.native",
                        "@class": "android.widget.ImageView",
                        "@text": "",
                        "@checkable": "false",
                        "@checked": "false",
                        "@clickable": "false",
                        "@enabled": "true",
                        "@focusable": "false",
                        "@focused": "false",
                        "@long-clickable": "false",
                        "@password": "false",
                        "@scrollable": "false",
                        "@selected": "false",
                        "@bounds": "[110,686][198,774]",
                        "@displayed": "true"
                      }
                    },
                    {
                      "@index": "4",
                      "@package": "com.opera.mini.native",
                      "@class": "android.widget.FrameLayout",
                      "@text": "",
                      "@checkable": "false",
                      "@checked": "false",
                      "@clickable": "false",
                      "@enabled": "true",
                      "@focusable": "false",
                      "@focused": "false",
                      "@long-clickable": "false",
                      "@password": "false",
                      "@scrollable": "false",
                      "@selected": "false",
                      "@bounds": "[66,835][1014,1001]",
                      "@displayed": "true",
                      "android.widget.LinearLayout": {
                        "@index": "0",
                        "@package": "com.opera.mini.native",
                        "@class": "android.widget.LinearLayout",
                        "@text": "",
                        "@resource-id": "com.opera.mini.native:id/save_data_switch",
                        "@checkable": "false",
                        "@checked": "false",
                        "@clickable": "true",
                        "@enabled": "true",
                        "@focusable": "true",
                        "@focused": "false",
                        "@long-clickable": "false",
                        "@password": "false",
                        "@scrollable": "false",
                        "@selected": "false",
                        "@bounds": "[66,835][1014,1001]",
                        "@displayed": "true",
                        "android.widget.LinearLayout": {
                          "@index": "0",
                          "@package": "com.opera.mini.native",
                          "@class": "android.widget.LinearLayout",
                          "@text": "",
                          "@checkable": "false",
                          "@checked": "false",
                          "@clickable": "false",
                          "@enabled": "true",
                          "@focusable": "false",
                          "@focused": "false",
                          "@long-clickable": "false",
                          "@password": "false",
                          "@scrollable": "false",
                          "@selected": "false",
                          "@bounds": "[220,862][838,973]",
                          "@displayed": "true",
                          "android.widget.TextView": {
                            "@index": "0",
                            "@package": "com.opera.mini.native",
                            "@class": "android.widget.TextView",
                            "@text": "Save data and browse longer",
                            "@resource-id": "com.opera.mini.native:id/caption",
                            "@checkable": "false",
                            "@checked": "false",
                            "@clickable": "false",
                            "@enabled": "true",
                            "@focusable": "false",
                            "@focused": "false",
                            "@long-clickable": "false",
                            "@password": "false",
                            "@scrollable": "false",
                            "@selected": "false",
                            "@bounds": "[220,862][816,973]",
                            "@displayed": "true"
                          }
                        },
                        "android.widget.Switch": {
                          "@index": "1",
                          "@package": "com.opera.mini.native",
                          "@class": "android.widget.Switch",
                          "@text": "ON",
                          "@resource-id": "com.opera.mini.native:id/switcher",
                          "@checkable": "true",
                          "@checked": "true",
                          "@clickable": "true",
                          "@enabled": "true",
                          "@focusable": "true",
                          "@focused": "false",
                          "@long-clickable": "false",
                          "@password": "false",
                          "@scrollable": "false",
                          "@selected": "false",
                          "@bounds": "[838,852][970,984]",
                          "@displayed": "true"
                        }
                      },
                      "android.widget.ImageView": {
                        "@index": "1",
                        "@package": "com.opera.mini.native",
                        "@class": "android.widget.ImageView",
                        "@text": "",
                        "@checkable": "false",
                        "@checked": "false",
                        "@clickable": "false",
                        "@enabled": "true",
                        "@focusable": "false",
                        "@focused": "false",
                        "@long-clickable": "false",
                        "@password": "false",
                        "@scrollable": "false",
                        "@selected": "false",
                        "@bounds": "[110,874][198,962]",
                        "@displayed": "true"
                      }
                    }
                  ]
                }
              },
              "android.widget.TextView": [
                {
                  "@index": "1",
                  "@package": "com.opera.mini.native",
                  "@class": "android.widget.TextView",
                  "@text": "Set as default browser",
                  "@resource-id": "com.opera.mini.native:id/set_as_default_browser_button",
                  "@checkable": "false",
                  "@checked": "false",
                  "@clickable": "true",
                  "@enabled": "true",
                  "@focusable": "true",
                  "@focused": "false",
                  "@long-clickable": "false",
                  "@password": "false",
                  "@scrollable": "false",
                  "@selected": "false",
                  "@bounds": "[265,1906][815,2027]",
                  "@displayed": "true"
                },
                {
                  "@index": "2",
                  "@package": "com.opera.mini.native",
                  "@class": "android.widget.TextView",
                  "@text": "Continue",
                  "@resource-id": "com.opera.mini.native:id/continue_button",
                  "@checkable": "false",
                  "@checked": "false",
                  "@clickable": "true",
                  "@enabled": "true",
                  "@focusable": "true",
                  "@focused": "false",
                  "@long-clickable": "false",
                  "@password": "false",
                  "@scrollable": "false",
                  "@selected": "false",
                  "@bounds": "[265,2071][815,2192]",
                  "@displayed": "true"
                }
              ]
            }
          }
        }
      },
      "android.view.View": {
        "@index": "2",
        "@package": "com.opera.mini.native",
        "@class": "android.view.View",
        "@text": "",
        "@resource-id": "android:id/navigationBarBackground",
        "@checkable": "false",
        "@checked": "false",
        "@clickable": "false",
        "@enabled": "true",
        "@focusable": "false",
        "@focused": "false",
        "@long-clickable": "false",
        "@password": "false",
        "@scrollable": "false",
        "@selected": "false",
        "@bounds": "[0,2236][1080,2280]",
        "@displayed": "true"
      }
    }
  }
}